simpson_rule/__init__.py
simpson_rule-0.1.dist-info/LICENSE.txt
simpson_rule-0.1.dist-info/METADATA
simpson_rule-0.1.dist-info/WHEEL
simpson_rule-0.1.dist-info/top_level.txt
simpson_rule-0.1.dist-info/RECORD
