Metadata-Version: 2.1
Name: simpson-rule
Version: 0.1
Summary: An ad-hoc numerical integration module
Author: Roberto Mulas
Author-email: rmulasgarcia@gmail.com
Classifier: Programming Language :: Python :: 3
Classifier: License :: OSI Approved :: MIT License
Classifier: Operating System :: OS Independent
License-File: LICENSE.txt
